allennlp_shiba/__init__.py
allennlp_shiba/common/__init__.py
allennlp_shiba/common/testing/__init__.py
allennlp_shiba/common/testing/test_case.py
allennlp_shiba/data/__init__.py
allennlp_shiba/data/token_indexers/__init__.py
allennlp_shiba/data/token_indexers/pretrained_shiba_indexer.py
allennlp_shiba/data/tokenizers/__init__.py
allennlp_shiba/data/tokenizers/codepoint_tokenizer.py
allennlp_shiba/modules/__init__.py
allennlp_shiba/modules/token_embedders/__init__.py
allennlp_shiba/modules/token_embedders/pretrained_shiba_embedder.py
allennlp_shiba-0.1.1.dist-info/LICENSE
allennlp_shiba-0.1.1.dist-info/WHEEL
allennlp_shiba-0.1.1.dist-info/METADATA
allennlp_shiba-0.1.1.dist-info/RECORD
