Metadata-Version: 2.1
Name: allennlp-shiba
Version: 0.1.1
Summary: AllenNLP integration for Shiba: Japanese CANINE model
Home-page: https://github.com/shunk031/allennlp-shiba-model
License: Apache-2.0
Keywords: natural language processing,deep learning,transformers,allennlp
Author: Shunsuke KITADA
Author-email: shunsuke.kitada.0831@gmail.com
Requires-Python: >=3.7,<4.0
Classifier: License :: OSI Approved :: Apache Software License
Classifier: Operating System :: OS Independent
Classifier: Programming Language :: Python :: 3
Classifier: Programming Language :: Python :: 3.7
Classifier: Programming Language :: Python :: 3.8
Classifier: Programming Language :: Python :: 3.9
Requires-Dist: allennlp (>=2.5.0,<3.0.0)
Requires-Dist: shiba-model (>=0.1.0,<0.2.0)
Project-URL: Repository, https://github.com/shunk031/allennlp-shiba-model
